<screen name="bouquetMakerXtreamAbout" position="0,0" size="1920,1080" backgroundColor="#2a70a4" flags="wfNoBorder">
	<ePixmap pixmap="/usr/lib/enigma2/python/Plugins/Extensions/BouquetMakerXtream/skin/fhd/slykq/images/background.jpg"  position="0,0" size="1920,1080" zPosition="-1"/>
	<widget source="global.CurrentTime" render="Label" position="1490,0" size="400,60" font="bmxregular;27" foregroundColor="#ffffff" backgroundColor="#2a70a4" valign="center" halign="right" transparent="1">
		<convert type="ClockToText">Format:%H:%M | %A %-d %b</convert>
	</widget>
	<ePixmap pixmap="/usr/lib/enigma2/python/Plugins/Extensions/BouquetMakerXtream/skin/fhd/common/logo.png" position="center,60" size="420,126" alphatest="blend" zPosition="1"/>
	<widget source="Title" render="Label" position="center,210" size="1920,70" foregroundColor="#ffffff" backgroundColor="#2a70a4" halign="center" font="bmxregular;48" transparent="1"/>
	<ePixmap pixmap="/usr/lib/enigma2/python/Plugins/Extensions/BouquetMakerXtream/skin/fhd/common/panel-wide.png" position="center,300" size="1680,660" alphatest="blend" zPosition="1"/>
	<widget name="about" position="center,309" size="1372,672" font="bmxregular;24" foregroundColor="#ffffff" backgroundColor="#2a70a4" valign="center" halign="center" transparent="1" zPosition="2"/>
	<ePixmap pixmap="/usr/lib/enigma2/python/Plugins/Extensions/BouquetMakerXtream/skin/fhd/common/button-bg.png" position="0,1020" size="1920,60" alphatest="blend" zPosition="1"/>
	<widget source="key_red" render="Pixmap" pixmap="/usr/lib/enigma2/python/Plugins/Extensions/BouquetMakerXtream/skin/fhd/common/key_red.png" position="750,1031" size="38,38" alphatest="blend" zPosition="2"/>
	<widget source="key_red" render="Label" position="802,1020" size="240,60" font="bmxregular;24" foregroundColor="#ffffff" backgroundColor="#0a3162" valign="center" transparent="1" noWrap="1" zPosition="2"/>
	<widget source="key_green" render="Pixmap" pixmap="/usr/lib/enigma2/python/Plugins/Extensions/BouquetMakerXtream/skin/fhd/common/key_green.png" position="1050,1031" size="38,38" alphatest="blend" zPosition="2"/>
	<widget source="key_green" render="Label" position="1102,1020" size="240,60" font="bmxregular;24" foregroundColor="#ffffff" backgroundColor="#0a3162" valign="center" transparent="1" noWrap="1" zPosition="2"/>
</screen>

